MANIFEST.in
setup.cfg
setup.py
sculpt/__init__.py
sculpt.debug.egg-info/PKG-INFO
sculpt.debug.egg-info/SOURCES.txt
sculpt.debug.egg-info/dependency_links.txt
sculpt.debug.egg-info/requires.txt
sculpt.debug.egg-info/top_level.txt
sculpt/debug/__init__.py
sculpt/debug/django_stub.py
sculpt/debug/templatetags/__init__.py
sculpt/debug/templatetags/pydump.py