Metadata-Version: 1.1
Name: sculpt.debug
Version: 0.1
Summary: A lightweight debugging display for Django.
Home-page: https://github.com/damienjones/sculpt-debug
Author: Damien M. Jones
Author-email: damien@codesculpture.com
License: LGPLv2
Platform: UNKNOWN
Classifier: Development Status :: 3 - Alpha
Classifier: License :: OSI Approved :: GNU Lesser General Public License v2 (LGPLv2)
Classifier: Programming Language :: Python :: 2
Classifier: Programming Language :: Python :: 2.6
Classifier: Programming Language :: Python :: 2.7
